shellev/__init__.py
shellev/api_helper.py
shellev/configuration.py
shellev/shellev_client.py
shellev/controllers/__init__.py
shellev/controllers/base_controller.py
shellev/controllers/charging_controller.py
shellev/controllers/locations_controller.py
shellev/controllers/o_auth_authorization_controller.py
shellev/exceptions/__init__.py
shellev/exceptions/api_exception.py
shellev/exceptions/bad_request_exception.py
shellev/exceptions/internal_server_error_exception.py
shellev/exceptions/not_found_exception.py
shellev/exceptions/o_auth_provider_exception.py
shellev/exceptions/serviceunavailable_exception.py
shellev/exceptions/too_many_requests_exception.py
shellev/exceptions/unauthorized_exception.py
shellev/http/__init__.py
shellev/http/http_call_back.py
shellev/http/http_method_enum.py
shellev/http/http_request.py
shellev/http/http_response.py
shellev/http/auth/__init__.py
shellev/http/auth/o_auth_2.py
shellev/models/__init__.py
shellev/models/accessibility.py
shellev/models/accessibility_status_enum.py
shellev/models/active_response_200_json.py
shellev/models/active_response_200_json_status_enum.py
shellev/models/address.py
shellev/models/bad_request_err_msg.py
shellev/models/charge_error.py
shellev/models/charge_retrieve_state.py
shellev/models/chargesession_start_body.py
shellev/models/connector_vo.py
shellev/models/connector_vo_connector_type_enum.py
shellev/models/connector_vo_updated_by_enum.py
shellev/models/coordinates.py
shellev/models/data_active.py
shellev/models/data_retrieve.py
shellev/models/electrical_properties.py
shellev/models/electrical_properties_power_type_enum.py
shellev/models/evse_vo.py
shellev/models/evse_vo_authorization_methods_enum.py
shellev/models/evse_vo_status_enum.py
shellev/models/get_charge_session_retrieve_response_200_json.py
shellev/models/get_charge_session_retrieve_response_200_json_status_enum.py
shellev/models/get_ev_locations_authorization_methods_enum.py
shellev/models/get_ev_locations_connector_types_enum.py
ev_recharge_sdk-1.4.0.dist-info/LICENSE
ev_recharge_sdk-1.4.0.dist-info/METADATA
ev_recharge_sdk-1.4.0.dist-info/WHEEL
ev_recharge_sdk-1.4.0.dist-info/top_level.txt
ev_recharge_sdk-1.4.0.dist-info/RECORD
