Metadata-Version: 2.2
Name: ev-recharge-sdk
Version: 1.4.0
Summary: This API Product provides the option to manage charging at all public Shell Recharge locations. The end points provides control to start, stop and get status of the charging session.
Author-email: developer sdksio <developer+sdksio@apimatic.io>
Project-URL: Documentation, https://developer.shell.com/product-catalog/shell-recharge/sdk#/http/setting-up-sdks
Keywords: EV,Charging,Shell,APIMatic,SDK,APIs,Recharge,locations
Requires-Python: >=3.7
License-File: LICENSE
Requires-Dist: apimatic-core>=0.2.17,~=0.2.0
Requires-Dist: apimatic-core-interfaces>=0.1.5,~=0.1.0
Requires-Dist: apimatic-requests-client-adapter>=0.1.6,~=0.1.0
Provides-Extra: testutils
Requires-Dist: pytest>=7.2.2; extra == "testutils"
